CirclesLocalLoggerPython/LoggerService.py
CirclesLocalLoggerPython/LoggerServiceSingleton.py
CirclesLocalLoggerPython/MessageSeverity.py
CirclesLocalLoggerPython/Writer.py
CirclesLocalLoggerPython/__init__.py
CirclesLocalLoggerPython/test_writer.py
src/LoggerService.py
src/LoggerServiceSingleton.py
src/MessageSeverity.py
src/Writer.py
src/__init__.py
local_logger_python_backend-0.0.2.dist-info/LICENSE
local_logger_python_backend-0.0.2.dist-info/METADATA
local_logger_python_backend-0.0.2.dist-info/WHEEL
local_logger_python_backend-0.0.2.dist-info/top_level.txt
local_logger_python_backend-0.0.2.dist-info/RECORD
